imgvision/__init__.py
imgvision/__version__.py
imgvision/.idea/.gitignore
imgvision/.idea/imgvision.iml
imgvision/.idea/misc.xml
imgvision/.idea/modules.xml
imgvision/.idea/workspace.xml
imgvision/.idea/inspectionProfiles/profiles_settings.xml
imgvision/data/A_D75.npy
imgvision/data/CIExyz_deg10.npy
imgvision/data/CIExyz_deg2.npy
imgvision/data/__init__.py
imgvision/data/a.npy
imgvision/data/b.npy
imgvision/data/c.npy
imgvision/data/cie64.npy
imgvision/data/d50.npy
imgvision/data/d55.npy
imgvision/data/d65.npy
imgvision/data/SRF/NikonD700.npy
imgvision/data/blur/kernel_m19.npy
paddleiv/__init__.py
paddleiv/__version__.py
paddleiv-0.0.0.6.dist-info/LICENSE
paddleiv-0.0.0.6.dist-info/METADATA
paddleiv-0.0.0.6.dist-info/WHEEL
paddleiv-0.0.0.6.dist-info/top_level.txt
paddleiv-0.0.0.6.dist-info/RECORD
