Metadata-Version: 2.1
Name: paddleiv
Version: 0.0.0.6
Summary: 适用于 Paddle2.0+ 的图像处理库
Home-page: https://github.com/Caoxuheng
Author: Xuheng Cao
Author-email: caoxuhengcn@gmail.com
License: UNKNOWN
Platform: UNKNOWN
Classifier: License :: OSI Approved :: MIT License
License-File: LICENSE
Requires-Dist: numpy
Requires-Dist: imgvision
